TheGreatCeoWithin/README.md
TheGreatCeoWithin/__init__.py
TheGreatCeoWithin/__main__.py
TheGreatCeoWithin/file.epub
TheGreatCeoWithin/index.html
TheGreatCeoWithin/css/__init__.py
TheGreatCeoWithin/css/annotations.css
TheGreatCeoWithin/css/main.css
TheGreatCeoWithin/css/normalize.css
TheGreatCeoWithin/css/popup.css
TheGreatCeoWithin/font/__init__.py
TheGreatCeoWithin/font/fontello.eot
TheGreatCeoWithin/font/fontello.svg
TheGreatCeoWithin/font/fontello.ttf
TheGreatCeoWithin/font/fontello.woff
TheGreatCeoWithin/img/__init__.py
TheGreatCeoWithin/img/annotator-glyph-sprite.png
TheGreatCeoWithin/img/annotator-icon-sprite.png
TheGreatCeoWithin/img/apple-touch-icon.png
TheGreatCeoWithin/img/cancelfullscreen.png
TheGreatCeoWithin/img/close.png
TheGreatCeoWithin/img/fullscreen.png
TheGreatCeoWithin/img/loader.gif
TheGreatCeoWithin/img/menu-icon.png
TheGreatCeoWithin/img/save.png
TheGreatCeoWithin/img/saved.png
TheGreatCeoWithin/img/settings-s.png
TheGreatCeoWithin/img/settings.png
TheGreatCeoWithin/img/star.png
TheGreatCeoWithin/js/__init__.py
TheGreatCeoWithin/js/epub.js
TheGreatCeoWithin/js/epub.min.js
TheGreatCeoWithin/js/epub.min.map
TheGreatCeoWithin/js/hooks.min.js
TheGreatCeoWithin/js/hooks.min.map
TheGreatCeoWithin/js/reader.js
TheGreatCeoWithin/js/reader.js.map
TheGreatCeoWithin/js/reader.min.js
TheGreatCeoWithin/js/reader.min.map
TheGreatCeoWithin/js/hooks/__init__.py
TheGreatCeoWithin/js/hooks/extensions/__init__.py
TheGreatCeoWithin/js/hooks/extensions/highlight.js
TheGreatCeoWithin/js/libs/__init__.py
TheGreatCeoWithin/js/libs/jquery.min.js
TheGreatCeoWithin/js/libs/localforage.min.js
TheGreatCeoWithin/js/libs/screenfull.js
TheGreatCeoWithin/js/libs/screenfull.min.js
TheGreatCeoWithin/js/libs/zip.min.js
TheGreatCeoWithin/js/plugins/__init__.py
TheGreatCeoWithin/js/plugins/hypothesis.js
TheGreatCeoWithin/js/plugins/search.js
the_great_ceo_within-2024.3.5.0.dist-info/METADATA
the_great_ceo_within-2024.3.5.0.dist-info/WHEEL
the_great_ceo_within-2024.3.5.0.dist-info/entry_points.txt
the_great_ceo_within-2024.3.5.0.dist-info/top_level.txt
the_great_ceo_within-2024.3.5.0.dist-info/RECORD
